sq3m/__init__.py
sq3m/main.py
sq3m/py.typed
sq3m/application/__init__.py
sq3m/application/services/__init__.py
sq3m/application/services/database_service.py
sq3m/application/services/table_search_service.py
sq3m/application/use_cases/__init__.py
sq3m/application/use_cases/database_analyzer.py
sq3m/application/use_cases/sql_generator.py
sq3m/config/__init__.py
sq3m/config/settings.py
sq3m/domain/__init__.py
sq3m/domain/entities/__init__.py
sq3m/domain/entities/database.py
sq3m/domain/entities/table_summary.py
sq3m/domain/interfaces/__init__.py
sq3m/domain/interfaces/database_repository.py
sq3m/domain/interfaces/llm_service.py
sq3m/domain/interfaces/table_search_repository.py
sq3m/infrastructure/__init__.py
sq3m/infrastructure/config/__init__.py
sq3m/infrastructure/config/env_detector.py
sq3m/infrastructure/database/__init__.py
sq3m/infrastructure/database/mysql_repository.py
sq3m/infrastructure/database/postgresql_repository.py
sq3m/infrastructure/database/repository_factory.py
sq3m/infrastructure/database/sqlite_table_search_repository.py
sq3m/infrastructure/history/__init__.py
sq3m/infrastructure/history/markdown_history.py
sq3m/infrastructure/llm/__init__.py
sq3m/infrastructure/llm/embedding_service.py
sq3m/infrastructure/llm/openai_service.py
sq3m/infrastructure/llm/translation_service.py
sq3m/infrastructure/prompts/__init__.py
sq3m/infrastructure/prompts/default_system_prompt_en.md
sq3m/infrastructure/prompts/prompt_loader.py
sq3m/interface/__init__.py
sq3m/interface/cli/__init__.py
sq3m/interface/cli/cli.py
sq3m-0.2.0.dist-info/METADATA
sq3m-0.2.0.dist-info/WHEEL
sq3m-0.2.0.dist-info/entry_points.txt
sq3m-0.2.0.dist-info/licenses/LICENSE
sq3m-0.2.0.dist-info/RECORD
