Metadata-Version: 2.4
Name: sq3m
Version: 0.2.0
Summary: Interactive CLI DB AI Agent for natural language to SQL conversion
Project-URL: Homepage, https://github.com/leegyurak/sq3m
Project-URL: Bug Reports, https://github.com/leegyurak/sq3m/issues
Project-URL: Source, https://github.com/leegyurak/sq3m
Author-email: leegyurak <dev@devgyurak.com>
License: MIT
License-File: LICENSE
Classifier: Development Status :: 3 - Alpha
Classifier: Intended Audience :: Developers
Classifier: License :: OSI Approved :: MIT License
Classifier: Programming Language :: Python :: 3
Classifier: Programming Language :: Python :: 3.10
Classifier: Programming Language :: Python :: 3.11
Classifier: Programming Language :: Python :: 3.12
Requires-Python: >=3.10
Requires-Dist: aiofiles>=24.1.0
Requires-Dist: click>=8.0.0
Requires-Dist: markdown>=3.5.0
Requires-Dist: openai>=1.0.0
Requires-Dist: psutil>=5.9.0
Requires-Dist: psycopg2-binary>=2.9.0
Requires-Dist: pydantic>=2.0.0
Requires-Dist: pymysql>=1.0.0
Requires-Dist: python-dotenv>=1.0.0
Requires-Dist: rich>=13.0.0
Requires-Dist: sqlparse>=0.4.0
Requires-Dist: types-aiofiles>=24.1.0.20250822
